COPYING
README.md
setup.cfg
setup.py
block/__init__.py
block/block_assemble.py
block/block_base.py
block/block_bc.py
block/block_compose.py
block/block_mat.py
block/block_scheme.py
block/block_transform.py
block/block_util.py
block/block_vec.py
block/dolfin_util.py
block/helpers.py
block/object_pool.py
block/splitting.py
block/testing.py
block/algebraic/__init__.py
block/algebraic/hazmath/__init__.py
block/algebraic/hazmath/precond.py
block/algebraic/petsc/__init__.py
block/algebraic/petsc/matrix.py
block/algebraic/petsc/precond.py
block/algebraic/trilinos/Amesos.py
block/algebraic/trilinos/AztecOO.py
block/algebraic/trilinos/Epetra.py
block/algebraic/trilinos/IFPACK.py
block/algebraic/trilinos/MLPrec.py
block/algebraic/trilinos/__init__.py
block/iterative/__init__.py
block/iterative/bicgstab.py
block/iterative/cgn.py
block/iterative/common.py
block/iterative/conjgrad.py
block/iterative/iterative.py
block/iterative/lgmres.py
block/iterative/minres.py
block/iterative/minres2.py
block/iterative/richardson.py
block/iterative/symmlq.py
block/iterative/tfqmr.py
cbc.block.egg-info/PKG-INFO
cbc.block.egg-info/SOURCES.txt
cbc.block.egg-info/dependency_links.txt
cbc.block.egg-info/requires.txt
cbc.block.egg-info/top_level.txt
test/test_block_transforms.py
test/test_discrete_ops.py
test/test_haz_precond.py