Metadata-Version: 2.1
Name: cbc.block
Version: 3.0.0
Summary: "Block algebra for Fenics/DOLFIN",
Home-page: https://github.com/blocknics/cbc.block
Author: Joachim Berdal Haga
Author-email: jobh@simula.no
License: LGPL-2.1-or-later
Platform: UNKNOWN
Requires-Python: >=3.8
Provides-Extra: haznics
Provides-Extra: test
Provides-Extra: trilinos
License-File: COPYING
